{"is_source_file": true, "format": "JavaScript", "description": "This file defines a Bootstrap JavaScript component for managing tabbed interfaces, including class definitions, event handling, and DOM manipulation logic.", "external_files": ["./base-component.js", "./dom/event-handler.js", "./dom/selector-engine.js", "./util/index.js"], "external_methods": ["defineJQueryPlugin", "getNextActiveElement", "isDisabled"], "published": ["Tab"], "classes": [{"name": "Tab", "description": "A class extending BaseComponent to implement tab navigation functionality, including methods for showing, activating, deactivating tabs, and handling keyboard navigation."}], "methods": [{"name": "show", "description": "Displays the tab associated with this instance, deactivating the currently active tab if any."}, {"name": "_activate", "description": "Activates a given tab element and its associated panel."}, {"name": "_deactivate", "description": "Deactivates a given tab element and its associated panel."}, {"name": "_keydown", "description": "Handles keyboard navigation between tabs."}, {"name": "_getChildren", "description": "Retrieves inner tab elements within the parent container."}, {"name": "_getActiveElem", "description": "Finds the currently active tab element."}, {"name": "_setInitialAttributes", "description": "Sets initial ARIA and role attributes on tab elements."}, {"name": "_setInitialAttributesOnChild", "description": "Sets initial attributes on individual tab elements."}, {"name": "_setInitialAttributesOnTargetPanel", "description": "Sets ARIA attributes on the tab panel associated with a tab."}, {"name": "_toggleDropDown", "description": "Handles toggling dropdown menu states if the tab is part of a dropdown."}, {"name": "_setAttributeIfNotExists", "description": "Sets an attribute on an element if it does not already have it."}, {"name": "_elemIsActive", "description": "Checks if a tab element is active."}, {"name": "_getInnerElement", "description": "Retrieves the inner element (like .nav-link) from a tab item."}, {"name": "_getOuterElement", "description": "Retrieves the outer element (like .nav-item) from a tab item."}, {"name": "jQueryInterface", "description": "Enables jQuery-style invocation of the Tab component."}], "calls": ["EventHandler.trigger", "SelectorEngine.find", "SelectorEngine.findOne", "Tab.getOrCreateInstance", "getNextActiveElement", "isDisabled", "defineJQueryPlugin"], "search-terms": ["Bootstrap tab component", "tab navigation JavaScript", "ARIA tab attributes", "Bootstrap dropdown tab", "Keyboard navigation tabs"], "state": 2, "file_id": 230, "knowledge_revision": 530, "git_revision": "1be3057230831b60f25044583a05b6682baead79", "ctags": [], "filename": "js/src/tab.js", "hash": "bfbf949f797c843547769fe180f409da", "format-version": 4, "code-base-name": "https://github.com/kavia-common/bootstrap-144031.git:kavia-astro-docs-getting-started", "revision_history": [{"530": "1be3057230831b60f25044583a05b6682baead79"}]}