{"is_source_file": true, "format": "JavaScript", "description": "This file defines the Bootstrap Alert component, including its class, methods for closing and destroying alert elements, and integration with jQuery. It imports dependencies and sets up constants and plugin registration.", "external_files": ["./base-component.js", "./dom/event-handler.js", "./util/component-functions.js", "./util/index.js"], "external_methods": ["EventHandler.trigger", "enableDismissTrigger", "defineJQueryPlugin"], "published": ["Alert"], "classes": [{"name": "Alert", "description": "A class representing the Bootstrap alert component, extending BaseComponent, with methods to close and destroy alert elements, and static methods for jQuery integration."}], "methods": [{"name": "close", "description": "Closes the alert by removing the show class and triggering the close event."}, {"name": "_destroyElement", "description": "Removes the alert element from the DOM and triggers the closed event."}, {"name": "jQueryInterface", "description": "Provides a jQuery plugin interface for the Alert component, allowing method calls via jQuery."}], "calls": ["EventHandler.trigger", "this._queueCallback", "this.dispose", "Alert.getOrCreateInstance", "defineJQueryPlugin", "enableDismissTrigger"], "search-terms": ["Bootstrap alert", "alert.js", "Alert class", "alert component", "Bootstrap JavaScript"], "state": 2, "file_id": 248, "knowledge_revision": 567, "git_revision": "ae43f0c48bf7acede8a325b24197001fe2b2f416", "ctags": [], "filename": "js/src/alert.js", "hash": "80ff55c3c069b954ccb2025daae99104", "format-version": 4, "code-base-name": "https://github.com/kavia-common/bootstrap-144031.git:kavia-astro-docs-getting-started", "revision_history": [{"567": "ae43f0c48bf7acede8a325b24197001fe2b2f416"}]}